mdfile/__init__.py
mdfile/code_to_md.py
mdfile/csv_to_md.py
mdfile/json_to_md.py
mdfile/md_factory.py
mdfile/md_to_md.py
mdfile/md_updater.py
mdfile/mdfile.py
mdfile/text_to_md.py
mdfile/to_markdown.py
mdfile-0.9.0.dist-info/licenses/LICENSE
mdfile-0.9.0.dist-info/METADATA
mdfile-0.9.0.dist-info/WHEEL
mdfile-0.9.0.dist-info/entry_points.txt
mdfile-0.9.0.dist-info/top_level.txt
mdfile-0.9.0.dist-info/RECORD
