Metadata-Version: 2.4
Name: mdfile
Version: 0.9.0
Summary: Process and update Markdown files with embedded file/process/var data.
Author-email: Chuck Bass <chuck@acrocad.net>
License-Expression: MIT
Project-URL: Homepage, https://github.com/hucker/mdfile
Keywords: markdown,CLI,markdown-processing
Requires-Python: <3.15,>=3.10
License-File: LICENSE
Requires-Dist: typer
Requires-Dist: rich
Dynamic: license-file
